docbinder_oss/__init__.py
docbinder_oss/main.py
docbinder_oss/cli/__init__.py
docbinder_oss/cli/search.py
docbinder_oss/cli/setup.py
docbinder_oss/cli/provider/__init__.py
docbinder_oss/cli/provider/get.py
docbinder_oss/cli/provider/list.py
docbinder_oss/cli/provider/test.py
docbinder_oss/core/schemas.py
docbinder_oss/helpers/__init__.py
docbinder_oss/helpers/config.py
docbinder_oss/helpers/path_utils.py
docbinder_oss/helpers/writers/base.py
docbinder_oss/helpers/writers/helper_functions.py
docbinder_oss/helpers/writers/multiformat_writer.py
docbinder_oss/helpers/writers/writer_console.py
docbinder_oss/helpers/writers/writer_csv.py
docbinder_oss/helpers/writers/writer_json.py
docbinder_oss/providers/__init__.py
docbinder_oss/providers/base_class.py
docbinder_oss/providers/google_drive/__init__.py
docbinder_oss/providers/google_drive/google_drive_buckets.py
docbinder_oss/providers/google_drive/google_drive_client.py
docbinder_oss/providers/google_drive/google_drive_files.py
docbinder_oss/providers/google_drive/google_drive_permissions.py
docbinder_oss/providers/google_drive/google_drive_service_config.py
docbinder_oss-0.1.3.dist-info/METADATA
docbinder_oss-0.1.3.dist-info/WHEEL
docbinder_oss-0.1.3.dist-info/entry_points.txt
docbinder_oss-0.1.3.dist-info/licenses/LICENSE
docbinder_oss-0.1.3.dist-info/RECORD
