Metadata-Version: 2.4
Name: docbinder_oss
Version: 0.1.3
Summary: DocBinder Open Source Shared Library
Author-email: Paolo Leonard <paolo@snappylab.dev>, Christophe Beke <christophe@snappylab.dev>
License-File: LICENSE
Requires-Python: >=3.11
Requires-Dist: google-api-python-client>=2.171.0
Requires-Dist: google-auth-oauthlib>=1.2.2
Requires-Dist: pydantic-settings>=2.9.1
Requires-Dist: pydantic>=2.11.5
Requires-Dist: pydantic[email]>=2.11.5
Requires-Dist: pyyaml>=6.0.2
Requires-Dist: rich>=14.0.0
Requires-Dist: typer>=0.16.0
